dace/__init__.py
dace/__version__.py
dace/config.ini
dace/dace.py
dace/astrometry/__init__.py
dace/astrometry/astrometry.py
dace/atmosphericSpectroscopy/__init__.py
dace/atmosphericSpectroscopy/atmosphericSpectroscopy.py
dace/catalog/__init__.py
dace/catalog/catalog.py
dace/cheops/__init__.py
dace/cheops/cheops.py
dace/exoplanet/__init__.py
dace/exoplanet/exoplanet.py
dace/imaging/__init__.py
dace/imaging/imaging.py
dace/lossy/__init__.py
dace/lossy/lossy.py
dace/opacity/__init__.py
dace/opacity/atom.py
dace/opacity/molecule.py
dace/opendata/__init__.py
dace/opendata/opendata.py
dace/photometry/__init__.py
dace/photometry/photometry.py
dace/population/__init__.py
dace/population/population.py
dace/spectroscopy/__init__.py
dace/spectroscopy/spectroscopy.py
dace/sun/__init__.py
dace/sun/sun.py
dace/target/__init__.py
dace/target/target.py
python_dace_client-2.1.1.dist-info/LICENSE.txt
python_dace_client-2.1.1.dist-info/METADATA
python_dace_client-2.1.1.dist-info/WHEEL
python_dace_client-2.1.1.dist-info/top_level.txt
python_dace_client-2.1.1.dist-info/RECORD
