Metadata-Version: 2.1
Name: python-dace-client
Version: 2.1.1
Summary: python-dace-client lets you query Dace backend with simple methods on each scientific field
Home-page: UNKNOWN
Author: Fabien ALESINA
Author-email: fabien.alesina@unige.ch
License: UNKNOWN
Platform: UNKNOWN
License-File: LICENSE.txt
Requires-Dist: requests (>=2.21.0)
Requires-Dist: astropy
Requires-Dist: numpy
Requires-Dist: pandas
